<?xml version="1.0" encoding="UTF-8"?>
<countryTR code="IRN" xmlns:xsi="http://www.w3.org/2001/XMLSchema-instance" xsi:noNamespaceSchemaLocation="http://imo.dmfa.si/schemas/CountryTeamResults.xsd">
<team year="2022">
<team_size>6</team_size><problem1>42</problem1><problem2>41</problem2><problem3>15</problem3><problem4>42</problem4><problem5>42</problem5><problem6>9</problem6><total>191</total><rank>8</rank><gold_medals>3</gold_medals><silver_medals>3</silver_medals><bronze_medals>0</bronze_medals><honourable_mentions>0</honourable_mentions></team><team year="2021">
<team_size>6</team_size><problem1>39</problem1><problem2>1</problem2><problem3>3</problem3><problem4>42</problem4><problem5>19</problem5><problem6>0</problem6><total>104</total><rank>29</rank><gold_medals>0</gold_medals><silver_medals>3</silver_medals><bronze_medals>3</bronze_medals><honourable_mentions>0</honourable_mentions></team><team year="2020">
<team_size>6</team_size><problem1>42</problem1><problem2>22</problem2><problem3>4</problem3><problem4>36</problem4><problem5>42</problem5><problem6>3</problem6><total>149</total><rank>18</rank><gold_medals>1</gold_medals><silver_medals>3</silver_medals><bronze_medals>2</bronze_medals><honourable_mentions>0</honourable_mentions></team><team year="2019">
<team_size>6</team_size><problem1>35</problem1><problem2>38</problem2><problem3>3</problem3><problem4>40</problem4><problem5>27</problem5><problem6>2</problem6><total>145</total><rank>23</rank><gold_medals>1</gold_medals><silver_medals>2</silver_medals><bronze_medals>3</bronze_medals><honourable_mentions>0</honourable_mentions></team><team year="2018">
<team_size>6</team_size><problem1>42</problem1><problem2>37</problem2><problem3>6</problem3><problem4>39</problem4><problem5>18</problem5><problem6>8</problem6><total>150</total><rank>19</rank><gold_medals>1</gold_medals><silver_medals>3</silver_medals><bronze_medals>1</bronze_medals><honourable_mentions>1</honourable_mentions></team><team year="2017">
<team_size>6</team_size><problem1>42</problem1><problem2>32</problem2><problem3>0</problem3><problem4>42</problem4><problem5>17</problem5><problem6>9</problem6><total>142</total><rank>5</rank><gold_medals>2</gold_medals><silver_medals>3</silver_medals><bronze_medals>1</bronze_medals><honourable_mentions>0</honourable_mentions></team><team year="2016">
<team_size>6</team_size><problem1>42</problem1><problem2>16</problem2><problem3>3</problem3><problem4>42</problem4><problem5>18</problem5><problem6>4</problem6><total>125</total><rank>24</rank><gold_medals>0</gold_medals><silver_medals>3</silver_medals><bronze_medals>3</bronze_medals><honourable_mentions>0</honourable_mentions></team><team year="2015">
<team_size>6</team_size><problem1>40</problem1><problem2>14</problem2><problem3>31</problem3><problem4>42</problem4><problem5>12</problem5><problem6>6</problem6><total>145</total><rank>7</rank><gold_medals>3</gold_medals><silver_medals>2</silver_medals><bronze_medals>1</bronze_medals><honourable_mentions>0</honourable_mentions></team><team year="2014">
<team_size>6</team_size><problem1>42</problem1><problem2>27</problem2><problem3>2</problem3><problem4>42</problem4><problem5>18</problem5><problem6>0</problem6><total>131</total><rank>21</rank><gold_medals>0</gold_medals><silver_medals>4</silver_medals><bronze_medals>2</bronze_medals><honourable_mentions>0</honourable_mentions></team><team year="2013">
<team_size>6</team_size><problem1>36</problem1><problem2>23</problem2><problem3>31</problem3><problem4>42</problem4><problem5>35</problem5><problem6>1</problem6><total>168</total><rank>10</rank><gold_medals>2</gold_medals><silver_medals>3</silver_medals><bronze_medals>1</bronze_medals><honourable_mentions>0</honourable_mentions></team><team year="2012">
<team_size>6</team_size><problem1>42</problem1><problem2>29</problem2><problem3>6</problem3><problem4>39</problem4><problem5>34</problem5><problem6>1</problem6><total>151</total><rank>8</rank><gold_medals>3</gold_medals><silver_medals>2</silver_medals><bronze_medals>1</bronze_medals><honourable_mentions>0</honourable_mentions></team><team year="2011">
<team_size>6</team_size><problem1>40</problem1><problem2>3</problem2><problem3>15</problem3><problem4>42</problem4><problem5>41</problem5><problem6>10</problem6><total>151</total><rank>10</rank><gold_medals>2</gold_medals><silver_medals>4</silver_medals><bronze_medals>0</bronze_medals><honourable_mentions>0</honourable_mentions></team><team year="2010">
<team_size>6</team_size><problem1>35</problem1><problem2>42</problem2><problem3>4</problem3><problem4>42</problem4><problem5>3</problem5><problem6>1</problem6><total>127</total><rank>16</rank><gold_medals>0</gold_medals><silver_medals>4</silver_medals><bronze_medals>2</bronze_medals><honourable_mentions>0</honourable_mentions></team><team year="2009">
<team_size>6</team_size><problem1>42</problem1><problem2>42</problem2><problem3>10</problem3><problem4>30</problem4><problem5>34</problem5><problem6>3</problem6><total>161</total><rank>15</rank><gold_medals>1</gold_medals><silver_medals>4</silver_medals><bronze_medals>1</bronze_medals><honourable_mentions>0</honourable_mentions></team><team year="2008">
<team_size>6</team_size><problem1>42</problem1><problem2>37</problem2><problem3>14</problem3><problem4>42</problem4><problem5>37</problem5><problem6>9</problem6><total>181</total><rank>5</rank><gold_medals>1</gold_medals><silver_medals>5</silver_medals><bronze_medals>0</bronze_medals><honourable_mentions>0</honourable_mentions></team><team year="2007">
<team_size>6</team_size><problem1>33</problem1><problem2>29</problem2><problem3>2</problem3><problem4>42</problem4><problem5>32</problem5><problem6>5</problem6><total>143</total><rank>12</rank><gold_medals>1</gold_medals><silver_medals>3</silver_medals><bronze_medals>2</bronze_medals><honourable_mentions>0</honourable_mentions></team><team year="2006">
<team_size>6</team_size><problem1>42</problem1><problem2>31</problem2><problem3>8</problem3><problem4>39</problem4><problem5>24</problem5><problem6>1</problem6><total>145</total><rank>8</rank><gold_medals>3</gold_medals><silver_medals>3</silver_medals><bronze_medals>0</bronze_medals><honourable_mentions>0</honourable_mentions></team><team year="2005">
<team_size>6</team_size><problem1>36</problem1><problem2>42</problem2><problem3>22</problem3><problem4>42</problem4><problem5>37</problem5><problem6>22</problem6><total>201</total><rank>4</rank><gold_medals>2</gold_medals><silver_medals>4</silver_medals><bronze_medals>0</bronze_medals><honourable_mentions>0</honourable_mentions></team><team year="2004">
<team_size>6</team_size><problem1>40</problem1><problem2>31</problem2><problem3>15</problem3><problem4>42</problem4><problem5>36</problem5><problem6>14</problem6><total>178</total><rank>9</rank><gold_medals>1</gold_medals><silver_medals>5</silver_medals><bronze_medals>0</bronze_medals><honourable_mentions>0</honourable_mentions></team><team year="2003">
<team_size>6</team_size><problem1>27</problem1><problem2>20</problem2><problem3>0</problem3><problem4>42</problem4><problem5>6</problem5><problem6>17</problem6><total>112</total><rank>17</rank><gold_medals>0</gold_medals><silver_medals>3</silver_medals><bronze_medals>2</bronze_medals><honourable_mentions>1</honourable_mentions></team><team year="2002">
<team_size>6</team_size><problem1>38</problem1><problem2>31</problem2><problem3>6</problem3><problem4>39</problem4><problem5>26</problem5><problem6>3</problem6><total>143</total><rank>11</rank><gold_medals>0</gold_medals><silver_medals>4</silver_medals><bronze_medals>2</bronze_medals><honourable_mentions>0</honourable_mentions></team><team year="2001">
<team_size>6</team_size><problem1>30</problem1><problem2>19</problem2><problem3>14</problem3><problem4>30</problem4><problem5>18</problem5><problem6>0</problem6><total>111</total><rank>18</rank><gold_medals>0</gold_medals><silver_medals>2</silver_medals><bronze_medals>4</bronze_medals><honourable_mentions>0</honourable_mentions></team><team year="2000">
<team_size>6</team_size><problem1>42</problem1><problem2>23</problem2><problem3>5</problem3><problem4>30</problem4><problem5>36</problem5><problem6>19</problem6><total>155</total><rank>10</rank><gold_medals>2</gold_medals><silver_medals>3</silver_medals><bronze_medals>1</bronze_medals><honourable_mentions>0</honourable_mentions></team><team year="1999">
<team_size>6</team_size><problem1>36</problem1><problem2>32</problem2><problem3>6</problem3><problem4>42</problem4><problem5>24</problem5><problem6>19</problem6><total>159</total><rank>8</rank><gold_medals>2</gold_medals><silver_medals>4</silver_medals><bronze_medals>0</bronze_medals><honourable_mentions>0</honourable_mentions></team><team year="1998">
<team_size>6</team_size><problem1>42</problem1><problem2>42</problem2><problem3>18</problem3><problem4>36</problem4><problem5>38</problem5><problem6>35</problem6><total>211</total><rank>1</rank><gold_medals>5</gold_medals><silver_medals>1</silver_medals><bronze_medals>0</bronze_medals><honourable_mentions>0</honourable_mentions></team><team year="1997">
<team_size>6</team_size><problem1>33</problem1><problem2>42</problem2><problem3>42</problem3><problem4>42</problem4><problem5>42</problem5><problem6>16</problem6><total>217</total><rank>3</rank><gold_medals>4</gold_medals><silver_medals>2</silver_medals><bronze_medals>0</bronze_medals><honourable_mentions>0</honourable_mentions></team><team year="1996">
<team_size>6</team_size><problem1>23</problem1><problem2>42</problem2><problem3>29</problem3><problem4>23</problem4><problem5>8</problem5><problem6>18</problem6><total>143</total><rank>9</rank><gold_medals>1</gold_medals><silver_medals>4</silver_medals><bronze_medals>1</bronze_medals><honourable_mentions>0</honourable_mentions></team><team year="1995">
<team_size>6</team_size><problem1>42</problem1><problem2>30</problem2><problem3>32</problem3><problem4>38</problem4><problem5>42</problem5><problem6>18</problem6><total>202</total><rank>8</rank><gold_medals>2</gold_medals><silver_medals>3</silver_medals><bronze_medals>1</bronze_medals><honourable_mentions>0</honourable_mentions></team><team year="1994">
<team_size>6</team_size><problem1>27</problem1><problem2>40</problem2><problem3>35</problem3><problem4>35</problem4><problem5>36</problem5><problem6>30</problem6><total>203</total><rank>8</rank><gold_medals>2</gold_medals><silver_medals>2</silver_medals><bronze_medals>2</bronze_medals><honourable_mentions>0</honourable_mentions></team><team year="1993">
<team_size>6</team_size><problem1>35</problem1><problem2>23</problem2><problem3>5</problem3><problem4>24</problem4><problem5>42</problem5><problem6>24</problem6><total>153</total><rank>6</rank><gold_medals>2</gold_medals><silver_medals>3</silver_medals><bronze_medals>1</bronze_medals><honourable_mentions>0</honourable_mentions></team><team year="1992">
<team_size>6</team_size><problem1>30</problem1><problem2>29</problem2><problem3>18</problem3><problem4>41</problem4><problem5>2</problem5><problem6>13</problem6><total>133</total><rank>14</rank><gold_medals>0</gold_medals><silver_medals>3</silver_medals><bronze_medals>2</bronze_medals><honourable_mentions>1</honourable_mentions></team><team year="1991">
<team_size>6</team_size><problem1>36</problem1><problem2>39</problem2><problem3>21</problem3><problem4>32</problem4><problem5>39</problem5><problem6>24</problem6><total>191</total><rank>8</rank><gold_medals>2</gold_medals><silver_medals>1</silver_medals><bronze_medals>2</bronze_medals><honourable_mentions>0</honourable_mentions></team><team year="1990">
<team_size>6</team_size><problem1>27</problem1><problem2>16</problem2><problem3>17</problem3><problem4>24</problem4><problem5>24</problem5><problem6>14</problem6><total>122</total><rank>14</rank><gold_medals>0</gold_medals><silver_medals>4</silver_medals><bronze_medals>0</bronze_medals><honourable_mentions>0</honourable_mentions></team><team year="1989">
<team_size>6</team_size><problem1>26</problem1><problem2>34</problem2><problem3>10</problem3><problem4>28</problem4><problem5>29</problem5><problem6>20</problem6><total>147</total><rank>14</rank><gold_medals>0</gold_medals><silver_medals>2</silver_medals><bronze_medals>3</bronze_medals><honourable_mentions>1</honourable_mentions></team><team year="1988">
<team_size>6</team_size><problem1>24</problem1><problem2>16</problem2><problem3>8</problem3><problem4>12</problem4><problem5>22</problem5><problem6>4</problem6><total>86</total><rank>20</rank><gold_medals>0</gold_medals><silver_medals>1</silver_medals><bronze_medals>3</bronze_medals><honourable_mentions>0</honourable_mentions></team><team year="1987">
<team_size>6</team_size><problem1>11</problem1><problem2>22</problem2><problem3>1</problem3><problem4>8</problem4><problem5>23</problem5><problem6>5</problem6><total>70</total><rank>26</rank><gold_medals>0</gold_medals><silver_medals>0</silver_medals><bronze_medals>1</bronze_medals><honourable_mentions></honourable_mentions></team><team year="1985">
<team_size>1</team_size><problem1>7</problem1><problem2>6</problem2><problem3>3</problem3><problem4>0</problem4><problem5>5</problem5><problem6>7</problem6><total>28</total><rank>31</rank><gold_medals>0</gold_medals><silver_medals>1</silver_medals><bronze_medals>0</bronze_medals><honourable_mentions></honourable_mentions></team></countryTR>